dashdash/__init__.py
dashdash/magic.py
tests/__init__.py
tests/helpers.py
tests/test_parser.py
tests/test_run.py
dashdash-0.0.0.dist-info/METADATA
dashdash-0.0.0.dist-info/WHEEL
dashdash-0.0.0.dist-info/top_level.txt
dashdash-0.0.0.dist-info/RECORD
