Metadata-Version: 2.1
Name: dashdash
Version: 0.0.0
Summary: Easiily turn a function into a command line app
Home-page: https://github.com/rcgale/dashdash
Author: Robert Gale
Author-email: rcgale@gmail.com
License: UNKNOWN
Platform: UNKNOWN
Requires-Dist: docstring-parser (>=0.7.3)
